witchat/__init__.py
witchat/cli.py
witchat/crypto.py
witchat/dht.py
witchat/storage.py
witchat/ui.py
witchat-0.2.2.dist-info/METADATA
witchat-0.2.2.dist-info/WHEEL
witchat-0.2.2.dist-info/entry_points.txt
witchat-0.2.2.dist-info/licenses/LICENSE
witchat-0.2.2.dist-info/RECORD
