Metadata-Version: 2.4
Name: witchat
Version: 0.2.2
Summary: An encrypted p2p chat app
Project-URL: Repository, https://github.com/vividsystem/witchat
Author: vividsystem
License: MIT License
License-File: LICENSE
Requires-Python: >=3.13
Requires-Dist: asyncio>=4.0.0
Requires-Dist: kademlia>=2.2.3
Requires-Dist: prompt-toolkit>=3.0.52
Requires-Dist: pynacl>=1.6.0
Requires-Dist: uvloop>=0.22.1
